.gitignore
MANIFEST.in
README.txt
bootstrap.py
buildout-plone41.cfg
buildout-plone42.cfg
buildout-plone43.cfg
setup.py
docs/CHANGES.txt
docs/CONTRIBUTORS.txt
docs/INSTALL.txt
docs/LICENSE.GPL
docs/LICENSE.txt
src/collective/__init__.py
src/collective.memberapproval.egg-info/PKG-INFO
src/collective.memberapproval.egg-info/SOURCES.txt
src/collective.memberapproval.egg-info/dependency_links.txt
src/collective.memberapproval.egg-info/entry_points.txt
src/collective.memberapproval.egg-info/namespace_packages.txt
src/collective.memberapproval.egg-info/not-zip-safe
src/collective.memberapproval.egg-info/requires.txt
src/collective.memberapproval.egg-info/top_level.txt
src/collective/memberapproval/__init__.py
src/collective/memberapproval/configure.zcml
src/collective/memberapproval/overrides.zcml
src/collective/memberapproval/setuphandlers.py
src/collective/memberapproval/browser/__init__.py
src/collective/memberapproval/browser/approval.pt
src/collective/memberapproval/browser/approval.py
src/collective/memberapproval/browser/configure.zcml
src/collective/memberapproval/browser/interfaces.py
src/collective/memberapproval/browser/overrides.zcml
src/collective/memberapproval/browser/usergroups.py
src/collective/memberapproval/browser/usergroups_usersoverview.pt
src/collective/memberapproval/profiles/default/browserlayer.xml
src/collective/memberapproval/profiles/default/collective.memberapproval.txt
src/collective/memberapproval/profiles/default/metadata.xml
src/collective/memberapproval/profiles/default/skins.xml
src/collective/memberapproval/skins/collective.memberapproval/registered.pt
src/collective/memberapproval/skins/collective.memberapproval/registered.pt.metadata
src/collective/memberapproval/skins/collective.memberapproval/registered_notify_template.pt
src/collective/memberapproval/skins/collective.memberapproval/registered_notify_template.pt.metadata
src/collective/memberapproval/tests/__init__.py
src/collective/memberapproval/tests/layer.py
src/collective/memberapproval/tests/test_approval.py