Metadata-Version: 1.1
Name: collective.memberapproval
Version: 1.0
Summary: Member approval for Plone
Home-page: http://svn.plone.org/svn/collective/
Author: Radim Novotny
Author-email: novotny.radim@gmail.com
License: GPL
Keywords: plone pas user-management
Platform: UNKNOWN
Classifier: Framework :: Plone
Classifier: Framework :: Plone :: 4.1
Classifier: Framework :: Plone :: 4.2
Classifier: Framework :: Plone :: 4.3
Classifier: Programming Language :: Python
Classifier: Programming Language :: Python :: 2.7
